{"zip": "570203", "sector": "Consumer Cyclical", "fullTimeEmployees": 150, "longBusinessSummary": "Northeast Electric Development Company Limited researches, designs, develops, produces, and sells products related to power transmission and transformation equipment in the People's Republic of China. The company also manufactures and sells electrical equipment, enclosed busbars, and other accessories; and provides hotel management, catering, and accommodation services. In addition, it offers engineering design, construction, reconnaissance, and consultation services for new energy projects, as well as electric power engineering service. The company was formerly known as Northeast Electricity Transmitting & Transformation Machinery Manufacturing Ltd. Northeast Electric Development Company Limited was founded in 1993 and is based in Haikou, the People's Republic of China.", "city": "Haikou", "phone": "86 89 8688 76008", "country": "China", "companyOfficers": [], "website": "http://nee.wsfg.hk", "maxAge": 1, "address1": "New HNA Building", "fax": "86 89 8688 76033", "industry": "Lodging", "address2": "22nd Floor No. 7 Guoxing Avenue Meilan District", "ebitdaMargins": -0.22521, "profitMargins": -0.92838997, "grossMargins": 0.38772, "operatingCashflow": -140284448, "revenueGrowth": 0.498, "operatingMargins": -0.26997, "ebitda": -18390260, "targetLowPrice": null, "recommendationKey": "none", "grossProfits": 27773198, "freeCashflow": -46480096, "targetMedianPrice": null, "currentPrice": 0.62, "earningsGrowth": -0.797, "currentRatio": 0.382, "returnOnAssets": -0.04019, "numberOfAnalystOpinions": null, "targetMeanPrice": null, "debtToEquity": null, "returnOnEquity": null, "targetHighPrice": null, "totalCash": 17032238, "totalDebt": 60694152, "totalRevenue": 81659544, "totalCashPerShare": 0.02, "financialCurrency": "CNY", "revenuePerShare": 0.089, "quickRatio": 0.31, "recommendationMean": null, "exchange": "HKG", "shortName": "NE ELECTRIC", "longName": "Northeast Electric Development Company Limited", "exchangeTimezoneName": "Asia/Hong_Kong", "exchangeTimezoneShortName": "HKT", "isEsgPopulated": false, "gmtOffSetMilliseconds": "28800000", "quoteType": "EQUITY", "symbol": "0042.HK", "messageBoardId": "finmb_8355123", "market": "hk_market", "annualHoldingsTurnover": null, "enterpriseToRevenue": 7.173, "beta3Year": null, "enterpriseToEbitda": -31.851, "52WeekChange": 0.29166663, "morningStarRiskRating": null, "forwardEps": null, "revenueQuarterlyGrowth": null, "sharesOutstanding": 257950000, "fundInceptionDate": null, "annualReportExpenseRatio": null, "totalAssets": null, "bookValue": -0.188, "sharesShort": null, "sharesPercentSharesOut": null, "fundFamily": null, "lastFiscalYearEnd": 1609372800, "heldPercentInstitutions": 0, "netIncomeToCommon": -75812024, "trailingEps": 0.012479, "lastDividendValue": 0.065, "SandP52WeekChange": 0.31910443, "priceToBook": null, "heldPercentInsiders": 0, "nextFiscalYearEnd": 1672444800, "yield": null, "mostRecentQuarter": 1632960000, "shortRatio": null, "sharesShortPreviousMonthDate": null, "floatShares": 657582441, "beta": null, "enterpriseValue": 585744064, "priceHint": 3, "threeYearAverageReturn": null, "lastSplitDate": null, "lastSplitFactor": null, "legalType": null, "lastDividendDate": 862531200, "morningStarOverallRating": null, "earningsQuarterlyGrowth": -0.797, "priceToSalesTrailing12Months": 17.886106, "dateShortInterest": null, "pegRatio": null, "ytdReturn": null, "forwardPE": null, "lastCapGain": null, "shortPercentOfFloat": null, "sharesShortPriorMonth": null, "impliedSharesOutstanding": 873369984, "category": null, "fiveYearAverageReturn": null, "previousClose": 0.62, "regularMarketOpen": 0.61, "twoHundredDayAverage": 0.6497122, "trailingAnnualDividendYield": null, "payoutRatio": 0, "volume24Hr": null, "regularMarketDayHigh": 0.61, "navPrice": null, "averageDailyVolume10Day": 580500, "regularMarketPreviousClose": 0.62, "fiftyDayAverage": 0.6555882, "trailingAnnualDividendRate": null, "open": 0.61, "toCurrency": null, "averageVolume10days": 580500, "expireDate": null, "algorithm": null, "dividendRate": null, "exDividendDate": 862531200, "circulatingSupply": null, "startDate": null, "regularMarketDayLow": 0.61, "currency": "HKD", "trailingPE": 49.683468, "regularMarketVolume": 36000, "lastMarket": null, "maxSupply": null, "openInterest": null, "marketCap": 1460571264, "volumeAllCurrencies": null, "strikePrice": null, "averageVolume": 837492, "dayLow": 0.61, "ask": 0.63, "askSize": 0, "volume": 36000, "fiftyTwoWeekHigh": 0.92, "fromCurrency": null, "fiveYearAvgDividendYield": null, "fiftyTwoWeekLow": 0.45, "bid": 0.61, "tradeable": false, "dividendYield": null, "bidSize": 0, "dayHigh": 0.61, "regularMarketPrice": 0.62, "preMarketPrice": null, "logo_url": "https://logo.clearbit.com/nee.wsfg.hk"}