{"zip": "310051", "sector": "Healthcare", "fullTimeEmployees": 6032, "longBusinessSummary": "Hangzhou Tigermed Consulting Co., Ltd. provides contract research organization services in China and internationally. It operates through Clinical Trial Solutions; and Clinical-Related and Laboratory Services. The company offers regulatory submission and approval, medical translation, and good manufacturing practice (GMP) consulting; clinical services in the areas of medical science, early clinical and late phase development, medical monitoring, project management, patient recruitment, and quality management system; and biometrics services covering data management, biostatistics, and statistical programming. It also provides integrated technology services, such as site management, pharmacovigilance, third party audit and training, medical imaging, clinical trial system solution, central laboratory, pre-clinical, and research hospital; medical device/ in vitro diagnostics (IVD) services comprising medical device testing, regulatory submission, clinical evaluation and trials, GMP certificate, EU MDR and IVDR preparation, and value added services; and post-marketing study, real world evidence, and vaccine clinical trial services. The company was incorporated in 2004 and is headquartered in Hangzhou, China.", "city": "Hangzhou", "phone": "86 57 1288 87227", "country": "China", "companyOfficers": [], "website": "http://www.tigermed.net", "maxAge": 1, "address1": "F18, Building A \u00e2\u0080\u0093 Shengda Science Park", "industry": "Diagnostics & Research", "address2": "Room 2001-2010, 20th Floor, Block 8 No. 19 Jugong Road Xixing Sub-District, Binjiang District", "ebitdaMargins": 0.30254, "profitMargins": 0.56627, "grossMargins": 0.47525, "operatingCashflow": 1148098816, "revenueGrowth": 0.387, "operatingMargins": 0.27667, "ebitda": 1041981056, "targetLowPrice": null, "recommendationKey": "none", "grossProfits": 1514243004, "freeCashflow": 471339104, "targetMedianPrice": null, "currentPrice": 147.49, "earningsGrowth": 0.529, "currentRatio": 8.564, "returnOnAssets": 0.04176, "numberOfAnalystOpinions": null, "targetMeanPrice": null, "debtToEquity": 2.986, "returnOnEquity": 0.20452999, "targetHighPrice": null, "totalCash": 9859069952, "totalDebt": 552810560, "totalRevenue": 3444121344, "totalCashPerShare": 11.3, "financialCurrency": "CNY", "revenuePerShare": 4.165, "quickRatio": 8.504, "recommendationMean": null, "exchange": "SHZ", "shortName": "HANGZHOU TIGERMED", "longName": "Hangzhou Tigermed Consulting Co., Ltd", "exchangeTimezoneName": "Asia/Shanghai", "exchangeTimezoneShortName": "CST", "isEsgPopulated": false, "gmtOffSetMilliseconds": "28800000", "underlyingSymbol": null, "quoteType": "EQUITY", "symbol": "300347.SZ", "underlyingExchangeSymbol": null, "headSymbol": null, "messageBoardId": "finmb_46839975", "uuid": "71e36c8a-73c5-3b45-98a1-b4feb76c0fa8", "market": "cn_market", "annualHoldingsTurnover": null, "enterpriseToRevenue": 45.585, "beta3Year": null, "enterpriseToEbitda": 150.674, "52WeekChange": null, "morningStarRiskRating": null, "forwardEps": 1.25, "revenueQuarterlyGrowth": null, "sharesOutstanding": 749342016, "fundInceptionDate": null, "annualReportExpenseRatio": null, "totalAssets": null, "bookValue": 18.823, "sharesShort": null, "sharesPercentSharesOut": null, "fundFamily": null, "lastFiscalYearEnd": 1609372800, "heldPercentInstitutions": 0.27271, "netIncomeToCommon": 1950295040, "trailingEps": 2.348, "lastDividendValue": null, "SandP52WeekChange": null, "priceToBook": 7.835627, "heldPercentInsiders": 0, "nextFiscalYearEnd": 1672444800, "yield": null, "mostRecentQuarter": 1617148800, "shortRatio": null, "sharesShortPreviousMonthDate": null, "floatShares": 613478054, "beta": 0.787668, "enterpriseValue": 156999680000, "priceHint": 2, "threeYearAverageReturn": null, "lastSplitDate": 1561939200, "lastSplitFactor": "1:1", "legalType": null, "morningStarOverallRating": null, "earningsQuarterlyGrowth": 0.786, "priceToSalesTrailing12Months": 36.039566, "dateShortInterest": null, "pegRatio": null, "ytdReturn": null, "forwardPE": 117.992004, "lastCapGain": null, "shortPercentOfFloat": null, "sharesShortPriorMonth": null, "category": null, "fiveYearAverageReturn": null, "previousClose": 151.38, "regularMarketOpen": 149.9, "twoHundredDayAverage": 165.37665, "trailingAnnualDividendYield": 0.0019817678, "payoutRatio": 0.1173, "volume24Hr": null, "regularMarketDayHigh": 152.34, "navPrice": null, "averageDailyVolume10Day": 7407990, "regularMarketPreviousClose": 151.38, "fiftyDayAverage": 168.15277, "trailingAnnualDividendRate": 0.3, "open": 149.9, "averageVolume10days": 7407990, "expireDate": null, "algorithm": null, "dividendRate": 0.3, "exDividendDate": 1622505600, "circulatingSupply": null, "startDate": null, "regularMarketDayLow": 147.37, "currency": "CNY", "trailingPE": 62.815163, "regularMarketVolume": 4129264, "lastMarket": null, "maxSupply": null, "openInterest": null, "marketCap": 124124643328, "volumeAllCurrencies": null, "strikePrice": null, "averageVolume": 7066018, "dayLow": 147.37, "ask": 147.46, "askSize": 0, "volume": 4129264, "fiftyTwoWeekHigh": 209.41, "fromCurrency": null, "fiveYearAvgDividendYield": null, "fiftyTwoWeekLow": 110.81, "bid": 147.34, "tradeable": false, "dividendYield": 0.0015, "bidSize": 0, "dayHigh": 152.34, "regularMarketPrice": 147.49, "preMarketPrice": null, "logo_url": "https://logo.clearbit.com/tigermed.net"}