{"sector": "Industrials", "fullTimeEmployees": 7964, "longBusinessSummary": "COSCO SHIPPING Development Co., Ltd., together with its subsidiaries, provides vessel chartering and container leasing services. The company manufactures and sells containers; and offers operating leasing, equity or debt investment, insurance brokerage, and cargo and liner agency services, as well as financial leasing services in the areas of medical services, education, new energy, and construction and industrial equipment. It also offers container management, management, property investment, trading, and commercial factoring services. As of December 31, 2020, the company had a container fleet of 77 vessels with a total capacity of 500,587 TEU; 5 bulk cargo vessels of 466,900 DWT each; 2 wood pulp carriers with a total capacity of 123,900 DWT; approximately 90 LNG vessels, heavy crane vessels, and oil tankers; and an inventory of containers of approximately 3.78 million TEU. It operates in Hong Kong, Mainland China, rest of Asia, the United States, Europe, and internationally. The company was formerly known as China Shipping Container Lines Company Limited and changed its name to COSCO SHIPPING Development Co., Ltd. in December 2016. COSCO SHIPPING Development Co., Ltd. was founded in 1997 and is headquartered in Shanghai, the People's Republic of China.", "city": "Shanghai", "phone": "86 21 6596 6105", "country": "China", "companyOfficers": [], "website": "http://development.coscoshipping.com", "maxAge": 1, "address1": "5299 Binjiang Dadao", "fax": "86 21 6596 6498", "industry": "Marine Shipping", "address2": "Pudong New Area", "ebitdaMargins": 0.33914003, "profitMargins": 0.12573, "grossMargins": 0.23801, "operatingCashflow": 10114995200, "revenueGrowth": 0.528, "operatingMargins": 0.17913, "ebitda": 7056117760, "targetLowPrice": 0.9, "recommendationKey": "none", "grossProfits": 4753405649, "freeCashflow": -40819085312, "targetMedianPrice": 0.9, "currentPrice": 3.25, "earningsGrowth": 1.683, "currentRatio": 0.586, "returnOnAssets": 0.015310001, "numberOfAnalystOpinions": 1, "targetMeanPrice": 0.9, "debtToEquity": 413.653, "returnOnEquity": 0.10183, "targetHighPrice": 0.9, "totalCash": 10823912448, "totalDebt": 111474475008, "totalRevenue": 20806154240, "totalCashPerShare": 0.939, "financialCurrency": "CNY", "revenuePerShare": 1.559, "quickRatio": 0.553, "recommendationMean": null, "exchange": "SHH", "shortName": "COSCO SHIPPING DEVELOPMENT CO L", "longName": "COSCO SHIPPING Development Co., Ltd.", "exchangeTimezoneName": "Asia/Shanghai", "exchangeTimezoneShortName": "CST", "isEsgPopulated": false, "gmtOffSetMilliseconds": "28800000", "underlyingSymbol": null, "quoteType": "EQUITY", "symbol": "601866.SS", "underlyingExchangeSymbol": null, "headSymbol": null, "messageBoardId": "finmb_5479768", "uuid": "4b3ceb93-36cb-38e5-8494-8ecc9f5d0cc2", "market": "cn_market", "annualHoldingsTurnover": null, "enterpriseToRevenue": 6.881, "beta3Year": null, "enterpriseToEbitda": 20.29, "52WeekChange": null, "morningStarRiskRating": null, "forwardEps": null, "revenueQuarterlyGrowth": null, "sharesOutstanding": 7932129792, "fundInceptionDate": null, "annualReportExpenseRatio": null, "totalAssets": null, "bookValue": 2.169, "sharesShort": null, "sharesPercentSharesOut": null, "fundFamily": null, "lastFiscalYearEnd": 1609372800, "heldPercentInstitutions": 0.01821, "netIncomeToCommon": 2616062720, "trailingEps": 0.196, "lastDividendValue": null, "SandP52WeekChange": null, "priceToBook": 1.4983864, "heldPercentInsiders": 0.59153, "nextFiscalYearEnd": 1672444800, "yield": null, "mostRecentQuarter": 1617062400, "shortRatio": null, "sharesShortPreviousMonthDate": null, "floatShares": 6692293087, "beta": 1.059483, "enterpriseValue": 143169290240, "priceHint": 4, "threeYearAverageReturn": null, "lastSplitDate": null, "lastSplitFactor": null, "legalType": null, "morningStarOverallRating": null, "earningsQuarterlyGrowth": 1.42, "priceToSalesTrailing12Months": 1.4709648, "dateShortInterest": null, "pegRatio": null, "ytdReturn": null, "forwardPE": null, "lastCapGain": null, "shortPercentOfFloat": null, "sharesShortPriorMonth": null, "category": null, "fiveYearAverageReturn": null, "previousClose": 3.3, "regularMarketOpen": 3.28, "twoHundredDayAverage": 3.5814085, "trailingAnnualDividendYield": 0.016969698, "payoutRatio": 0.22770001, "volume24Hr": null, "regularMarketDayHigh": 3.34, "navPrice": null, "averageDailyVolume10Day": 58744942, "regularMarketPreviousClose": 3.3, "fiftyDayAverage": 3.956389, "trailingAnnualDividendRate": 0.056, "open": 3.28, "averageVolume10days": 58744942, "expireDate": null, "algorithm": null, "dividendRate": 0.06, "exDividendDate": 1627430400, "circulatingSupply": null, "startDate": null, "regularMarketDayLow": 3.25, "currency": "CNY", "trailingPE": 16.581633, "regularMarketVolume": 33634101, "lastMarket": null, "maxSupply": null, "openInterest": null, "marketCap": 30605119488, "volumeAllCurrencies": null, "strikePrice": null, "averageVolume": 111628139, "dayLow": 3.25, "ask": 3.26, "askSize": null, "volume": 33634101, "fiftyTwoWeekHigh": 5.11, "fromCurrency": null, "fiveYearAvgDividendYield": null, "fiftyTwoWeekLow": 2.25, "bid": 3.25, "tradeable": false, "dividendYield": 0.016, "bidSize": null, "dayHigh": 3.34, "regularMarketPrice": 3.25, "preMarketPrice": null, "logo_url": "https://logo.clearbit.com/development.coscoshipping.com"}